accordo_cli/__init__.py
accordo_cli/main.py
accordo_cli/handlers/__init__.py
accordo_cli/handlers/base.py
accordo_cli/handlers/claude.py
accordo_cli/handlers/cursor.py
accordo_cli/handlers/vscode.py
accordo_cli/models/__init__.py
accordo_cli/models/config.py
accordo_cli/models/platform.py
accordo_cli/utils/__init__.py
accordo_cli/utils/bootstrap.py
accordo_cli/utils/prompts.py
accordo_workflow_mcp/__init__.py
accordo_workflow_mcp/config.py
accordo_workflow_mcp/server.py
accordo_workflow_mcp/models/__init__.py
accordo_workflow_mcp/models/cache_models.py
accordo_workflow_mcp/models/config.py
accordo_workflow_mcp/models/responses.py
accordo_workflow_mcp/models/workflow_state.py
accordo_workflow_mcp/models/yaml_workflow.py
accordo_workflow_mcp/prompts/__init__.py
accordo_workflow_mcp/prompts/discovery_prompts.py
accordo_workflow_mcp/prompts/phase_prompts.py
accordo_workflow_mcp/services/__init__.py
accordo_workflow_mcp/services/cache_service.py
accordo_workflow_mcp/services/config_service.py
accordo_workflow_mcp/services/dependency_injection.py
accordo_workflow_mcp/services/session_lifecycle_manager.py
accordo_workflow_mcp/services/session_repository.py
accordo_workflow_mcp/services/session_service_factory.py
accordo_workflow_mcp/services/session_sync_service.py
accordo_workflow_mcp/services/workflow_definition_cache.py
accordo_workflow_mcp/utils/__init__.py
accordo_workflow_mcp/utils/cache_manager.py
accordo_workflow_mcp/utils/config_helpers.py
accordo_workflow_mcp/utils/config_utils.py
accordo_workflow_mcp/utils/markdown_generator.py
accordo_workflow_mcp/utils/node_executor.py
accordo_workflow_mcp/utils/path_utils.py
accordo_workflow_mcp/utils/placeholder_processor.py
accordo_workflow_mcp/utils/schema_analyzer.py
accordo_workflow_mcp/utils/session_id_utils.py
accordo_workflow_mcp/utils/session_manager.py
accordo_workflow_mcp/utils/state_manager.py
accordo_workflow_mcp/utils/template_generator.py
accordo_workflow_mcp/utils/test_utils.py
accordo_workflow_mcp-0.8.3.dist-info/licenses/LICENSE
accordo_workflow_mcp-0.8.3.dist-info/METADATA
accordo_workflow_mcp-0.8.3.dist-info/WHEEL
accordo_workflow_mcp-0.8.3.dist-info/entry_points.txt
accordo_workflow_mcp-0.8.3.dist-info/top_level.txt
accordo_workflow_mcp-0.8.3.dist-info/RECORD
