Metadata-Version: 2.4
Name: accordo-workflow-mcp
Version: 0.8.3
Summary: Accordo MCP server with dynamic YAML workflow support
Requires-Python: >=3.12
License-File: LICENSE
Requires-Dist: fastmcp
Requires-Dist: pydantic
Requires-Dist: PyYAML
Requires-Dist: typer
Requires-Dist: chromadb>=0.4.0
Requires-Dist: sentence-transformers>=2.2.0
Provides-Extra: dev
Requires-Dist: ruff; extra == "dev"
Requires-Dist: pytest>=7.0.0; extra == "dev"
Requires-Dist: pytest-asyncio>=0.21.0; extra == "dev"
Requires-Dist: pytest-cov>=4.0.0; extra == "dev"
Requires-Dist: pytest-mock>=3.10.0; extra == "dev"
Requires-Dist: twine; extra == "dev"
Dynamic: license-file
